<?xml version="1.0" encoding="UTF-8"?>
	<!DOCTYPE tv SYSTEM "http://www.w3.org/2006/05/tv"><tv version="" encoding=""><channel id="143"><display-name>CNBC TV18 Prime</display-name></channel><channel id="144"><display-name>Colors HD</display-name></channel><channel id="146"><display-name>History TV18 HD</display-name></channel><channel id="151"><display-name>Movies Now HD</display-name></channel><channel id="154"><display-name>Sony SAB</display-name></channel><channel id="155"><display-name>Sony Ten 5 HD</display-name></channel><channel id="156"><display-name>Star Gold HD</display-name></channel><channel id="162"><display-name>Sony Ten 1 HD</display-name></channel><channel id="164"><display-name>Travelxp HD</display-name></channel><channel id="166"><display-name>Cartoon Network Telugu</display-name></channel><channel id="173"><display-name>Aaj Tak</display-name></channel><channel id="175"><display-name>Aastha</display-name></channel><channel id="177"><display-name>ABP News India</display-name></channel><channel id="180"><display-name>Asianet News</display-name></channel><channel id="182"><display-name>B4U Movies</display-name></channel><channel id="183"><display-name>B4U Music</display-name></channel><channel id="190"><display-name>CNBC Awaaz</display-name></channel><channel id="193"><display-name>CNN</display-name></channel><channel id="196"><display-name>Colors Gujarati</display-name></channel><channel id="202"><display-name>DD National</display-name></channel><channel id="203"><display-name>DD News</display-name></channel><channel id="204"><display-name>DD Sports</display-name></channel><channel id="212"><display-name>ET Now</display-name></channel><channel id="231"><display-name>News 18 India</display-name></channel><channel id="232"><display-name>News18 Marathi</display-name></channel><channel id="235"><display-name>India TV</display-name></channel><channel id="242"><display-name>Discovery English</display-name></channel><channel id="248"><display-name>MTV</display-name></channel><channel id="250"><display-name>Music India</display-name></channel><channel id="252"><display-name>ETV Cinema</display-name></channel><channel id="255"><display-name>NDTV 24x7</display-name></channel><channel id="258"><display-name>NDTV India</display-name></channel><channel id="259"><display-name>NDTV Profit</display-name></channel><channel id="279"><display-name>Colors Rishtey</display-name></channel><channel id="286"><display-name>Animal Planet HD English</display-name></channel><channel id="288"><display-name>Sanskar</display-name></channel><channel id="289"><display-name>Sony Max SD</display-name></channel><channel id="290"><display-name>sonic Tamil</display-name></channel><channel id="291"><display-name>SET HD</display-name></channel><channel id="317"><display-name>Star Jalsha HD</display-name></channel><channel id="336"><display-name>Star Pravah HD</display-name></channel><channel id="368"><display-name>Star Vijay HD</display-name></channel><channel id="370"><display-name>Suvarna HD</display-name></channel><channel id="383"><display-name>Times NOW</display-name></channel><channel id="400"><display-name>PM e Vidya 01</display-name></channel><channel id="401"><display-name>Swayam Prabha 19</display-name></channel><channel id="402"><display-name>PM e Vidya 02</display-name></channel><channel id="403"><display-name>Swayam Prabha 20</display-name></channel><channel id="404"><display-name>PM e Vidya 07</display-name></channel><channel id="405"><display-name>PM e Vidya 03</display-name></channel><channel id="406"><display-name>PM e Vidya 04</display-name></channel><channel id="407"><display-name>PM e Vidya 05</display-name></channel><channel id="408"><display-name>PM e Vidya 06</display-name></channel><channel id="409"><display-name>PM e Vidya 08</display-name></channel><channel id="410"><display-name>PM e Vidya 09</display-name></channel><channel id="411"><display-name>PM e Vidya 10</display-name></channel><channel id="412"><display-name>Wion</display-name></channel><channel id="417"><display-name>J Movies</display-name></channel><channel id="418"><display-name>Jaya Plus</display-name></channel><channel id="419"><display-name>Jaya TV HD</display-name></channel><channel id="420"><display-name>Jaya Max</display-name></channel><channel id="421"><display-name>GOA 365</display-name></channel><channel id="422"><display-name>In Goa 24x7</display-name></channel><channel id="429"><display-name>Colors Tamil HD</display-name></channel><channel id="440"><display-name>9X Jalwa</display-name></channel><channel id="441"><display-name>9x Jhakaas</display-name></channel><channel id="442"><display-name>Zee 24 Taas</display-name></channel><channel id="443"><display-name>Asianet HD</display-name></channel><channel id="457"><display-name>Jalsha Movies HD</display-name></channel><channel id="459"><display-name>Asianet Movies HD</display-name></channel><channel id="463"><display-name>Discovery HD English</display-name></channel><channel id="464"><display-name>Zee 24 Ghanta</display-name></channel><channel id="465"><display-name>Jaihind tv</display-name></channel><channel id="466"><display-name>Dharma Sandesh</display-name></channel><channel id="471"><display-name>Sony SAB HD</display-name></channel><channel id="474"><display-name>Sony Pal</display-name></channel><channel id="476"><display-name>Sony Max HD</display-name></channel><channel id="477"><display-name>MN+ HD</display-name></channel><channel id="479"><display-name>TLC HD English</display-name></channel><channel id="482"><display-name>Colors Cineplex</display-name></channel><channel id="483"><display-name>Sony MAX2</display-name></channel><channel id="489"><display-name>CNBC TV18</display-name></channel><channel id="490"><display-name>CNBC Bajar</display-name></channel><channel id="491"><display-name>Mirror Now</display-name></channel><channel id="492"><display-name>CNN NEWS18</display-name></channel><channel id="493"><display-name>India Today</display-name></channel><channel id="494"><display-name>AL Jazeera</display-name></channel><channel id="495"><display-name>News X</display-name></channel><channel id="496"><display-name>dw</display-name></channel><channel id="498"><display-name>India news</display-name></channel><channel id="499"><display-name>News Nation</display-name></channel><channel id="501"><display-name>News 24</display-name></channel><channel id="502"><display-name>Good News Today</display-name></channel><channel id="503"><display-name>IBC24</display-name></channel><channel id="504"><display-name>Zee News</display-name></channel><channel id="510"><display-name>VIP News</display-name></channel><channel id="511"><display-name>Mh One News</display-name></channel><channel id="512"><display-name>India News UP</display-name></channel><channel id="513"><display-name>India News Rajasthan</display-name></channel><channel id="514"><display-name>Sony Ten 1</display-name></channel><channel id="515"><display-name>India News MP</display-name></channel><channel id="516"><display-name>India News Haryana</display-name></channel><channel id="517"><display-name>Chardikla Time TV</display-name></channel><channel id="518"><display-name>Sudarshan</display-name></channel><channel id="519"><display-name>Sadhna News Plus</display-name></channel><channel id="520"><display-name>Sansad TV HD</display-name></channel><channel id="522"><display-name>Sansad TV</display-name></channel><channel id="523"><display-name>Ten 2</display-name></channel><channel id="524"><display-name>Sony Ten 3 Hindi</display-name></channel><channel id="525"><display-name>Sony Ten 5</display-name></channel><channel id="527"><display-name>Investigation Discovery Hindi</display-name></channel><channel id="528"><display-name>DD India</display-name></channel><channel id="529"><display-name>News18 MP Chhattisgarh</display-name></channel><channel id="530"><display-name>News18 UP Uttarakhand</display-name></channel><channel id="531"><display-name>News18 Rajasthan</display-name></channel><channel id="533"><display-name>Raj Pariwar</display-name></channel><channel id="536"><display-name>DD Madhya Pradesh</display-name></channel><channel id="538"><display-name>DD Rajasthan (Jaipur)</display-name></channel><channel id="539"><display-name>DD Bihar</display-name></channel><channel id="540"><display-name>DD Uttar Pradesh</display-name></channel><channel id="541"><display-name>Discovery Turbo</display-name></channel><channel id="542"><display-name>Pogo Tamil</display-name></channel><channel id="543"><display-name>Nick Telugu</display-name></channel><channel id="544"><display-name>Nick Junior</display-name></channel><channel id="545"><display-name>Nick Hindi</display-name></channel><channel id="546"><display-name>Nick Tamil</display-name></channel><channel id="548"><display-name>Nickelodeon Jr.</display-name></channel><channel id="550"><display-name>Discovery Kids Tamil</display-name></channel><channel id="551"><display-name>TEST14 HD</display-name></channel><channel id="554"><display-name>Discovery Kids Hindi</display-name></channel><channel id="555"><display-name>Chintu TV</display-name></channel><channel id="556"><display-name>Kochu TV</display-name></channel><channel id="557"><display-name>Chutti TV</display-name></channel><channel id="558"><display-name>Kushi TV</display-name></channel><channel id="559"><display-name>Pogo Hindi</display-name></channel><channel id="560"><display-name>GOOD TiMES</display-name></channel><channel id="561"><display-name>Food Food</display-name></channel><channel id="562"><display-name>Travelxp HD Hindi</display-name></channel><channel id="563"><display-name>Kaumudy TV</display-name></channel><channel id="565"><display-name>ETV Abhiruchi</display-name></channel><channel id="566"><display-name>Animal Planet Hindi</display-name></channel><channel id="567"><display-name>Animal Planet English</display-name></channel><channel id="568"><display-name>Discovery Science English</display-name></channel><channel id="569"><display-name>D Tamil</display-name></channel><channel id="570"><display-name>ETV Life</display-name></channel><channel id="571"><display-name>TLC Hindi</display-name></channel><channel id="572"><display-name>Zee UP UK</display-name></channel><channel id="573"><display-name>Discovery Bengali</display-name></channel><channel id="574"><display-name>TLC English</display-name></channel><channel id="575"><display-name>Discovery Hindi</display-name></channel><channel id="576"><display-name>Discovery Telugu</display-name></channel><channel id="577"><display-name>History TV18 HD Telugu</display-name></channel><channel id="578"><display-name>History TV18 HD Hindi</display-name></channel><channel id="579"><display-name>History TV18 HD Tamil</display-name></channel><channel id="580"><display-name>DD bharati</display-name></channel><channel id="583"><display-name>DD Kisan</display-name></channel><channel id="587"><display-name>9XM</display-name></channel><channel id="591"><display-name>E 24</display-name></channel><channel id="592"><display-name>ZOOM</display-name></channel><channel id="593"><display-name>Sadhna</display-name></channel><channel id="594"><display-name>Aastha Bhajan</display-name></channel><channel id="595"><display-name>Prarthana Life</display-name></channel><channel id="596"><display-name>Jinvani TV</display-name></channel><channel id="597"><display-name>Satsang TV</display-name></channel><channel id="598"><display-name>Sri Venkateshwar Bhakti</display-name></channel><channel id="599"><display-name>Disha tv</display-name></channel><channel id="601"><display-name>Ishwar TV</display-name></channel><channel id="602"><display-name>Paras tv</display-name></channel><channel id="603"><display-name>Nambikkai</display-name></channel><channel id="605"><display-name>Channel Win</display-name></channel><channel id="606"><display-name>Shalom</display-name></channel><channel id="607"><display-name>Subhavartha TV</display-name></channel><channel id="608"><display-name>Shubhsandesh TV</display-name></channel><channel id="609"><display-name>mh1 Shraddha</display-name></channel><channel id="611"><display-name>Darshan 24</display-name></channel><channel id="612"><display-name>ABP Majha</display-name></channel><channel id="613"><display-name>Newslive</display-name></channel><channel id="614"><display-name>ETV Andhra pradesh</display-name></channel><channel id="615"><display-name>News18 Tamil nadu</display-name></channel><channel id="616"><display-name>TV9 Gujarat</display-name></channel><channel id="617"><display-name>TV9 Maharashtra</display-name></channel><channel id="618"><display-name>TV9 Telugu News</display-name></channel><channel id="619"><display-name>TV9 Karnataka</display-name></channel><channel id="620"><display-name>News18 Gujarati</display-name></channel><channel id="623"><display-name>Rang</display-name></channel><channel id="624"><display-name>Prag News</display-name></channel><channel id="626"><display-name>Suvarna News</display-name></channel><channel id="627"><display-name>News18 Assam NE</display-name></channel><channel id="629"><display-name>ETV Telugu</display-name></channel><channel id="630"><display-name>ETV Telangana</display-name></channel><channel id="631"><display-name>MBC</display-name></channel><channel id="632"><display-name>Sakshi tv</display-name></channel><channel id="633"><display-name>DY 365</display-name></channel><channel id="634"><display-name>Flower TV</display-name></channel><channel id="636"><display-name>Polimer News</display-name></channel><channel id="637"><display-name>North East Live</display-name></channel><channel id="639"><display-name>Ramdhenu</display-name></channel><channel id="641"><display-name>ABP Asmita</display-name></channel><channel id="642"><display-name>VTV Gujarati</display-name></channel><channel id="643"><display-name>GS TV</display-name></channel><channel id="646"><display-name>NTV</display-name></channel><channel id="647"><display-name>Pratidin Time</display-name></channel><channel id="648"><display-name>Mazhavil Manorama</display-name></channel><channel id="650"><display-name>Raj News Malayalam</display-name></channel><channel id="651"><display-name>Raj News Kannada</display-name></channel><channel id="652"><display-name>Zee Bharat</display-name></channel><channel id="653"><display-name>News18 Kannada</display-name></channel><channel id="654"><display-name>Zee Punjab Haryana HP</display-name></channel><channel id="655"><display-name>News18 Punjab Haryana Himachal</display-name></channel><channel id="656"><display-name>News 9</display-name></channel><channel id="657"><display-name>Zee Business</display-name></channel><channel id="658"><display-name>Zee MP Chattisgarh</display-name></channel><channel id="659"><display-name>Zee Rajasthan</display-name></channel><channel id="661"><display-name>Zee Bihar Jharkhand</display-name></channel><channel id="662"><display-name>Manorama News</display-name></channel><channel id="664"><display-name>Raj News Telugu</display-name></channel><channel id="665"><display-name>HM TV</display-name></channel><channel id="666"><display-name>ABN Andhra Jyothi</display-name></channel><channel id="667"><display-name>T News</display-name></channel><channel id="668"><display-name>TV 5 News</display-name></channel><channel id="670"><display-name>6 TV</display-name></channel><channel id="671"><display-name>Sathiyam TV</display-name></channel><channel id="672"><display-name>ABP Ananda</display-name></channel><channel id="673"><display-name>News7 Tamil</display-name></channel><channel id="675"><display-name>Assam Talks</display-name></channel><channel id="676"><display-name>Sun News</display-name></channel><channel id="677"><display-name>Puthiya Thalimurai</display-name></channel><channel id="678"><display-name>Sun Udaya Movies</display-name></channel><channel id="682"><display-name>Sun Life</display-name></channel><channel id="683"><display-name>Raj Digital Plus</display-name></channel><channel id="684"><display-name>Sun Gemini Life</display-name></channel><channel id="686"><display-name>Alankar</display-name></channel><channel id="687"><display-name>News Time TV</display-name></channel><channel id="690"><display-name>DD Bangla</display-name></channel><channel id="691"><display-name>Saam Tv</display-name></channel><channel id="692"><display-name>ETV Plus</display-name></channel><channel id="693"><display-name>news18 Bihar Jharkhand</display-name></channel><channel id="694"><display-name>News18 Delhi NCR JK</display-name></channel><channel id="695"><display-name>DD Sahayadri</display-name></channel><channel id="696"><display-name>News18 Odia</display-name></channel><channel id="697"><display-name>Sony aath</display-name></channel><channel id="698"><display-name>Aakash Aath</display-name></channel><channel id="699"><display-name>DD Malayalam</display-name></channel><channel id="702"><display-name>DD Oriya</display-name></channel><channel id="703"><display-name>Tarang</display-name></channel><channel id="704"><display-name>OTV</display-name></channel><channel id="705"><display-name>Polimer TV</display-name></channel><channel id="706"><display-name>DD Saptagiri</display-name></channel><channel id="707"><display-name>Raj TV</display-name></channel><channel id="708"><display-name>Makkal TV</display-name></channel><channel id="709"><display-name>Adithya TV</display-name></channel><channel id="710"><display-name>Kairali TV</display-name></channel><channel id="712"><display-name>DD urdu</display-name></channel><channel id="713"><display-name>DD9 chandana (kannada)</display-name></channel><channel id="714"><display-name>DD Girnar</display-name></channel><channel id="715"><display-name>DD Punjabi</display-name></channel><channel id="716"><display-name>DD Kashir</display-name></channel><channel id="717"><display-name>News18 Bangla</display-name></channel><channel id="718"><display-name>Kanak News</display-name></channel><channel id="719"><display-name>Nepal one</display-name></channel><channel id="723"><display-name>Amrita TV</display-name></channel><channel id="724"><display-name>Zee Delhi NCR Haryana</display-name></channel><channel id="725"><display-name>Kairali News</display-name></channel><channel id="726"><display-name>DD5 Podhigai</display-name></channel><channel id="727"><display-name>Vasanth TV</display-name></channel><channel id="728"><display-name>Salaam TV</display-name></channel><channel id="729"><display-name>Sun Gemini Comedy</display-name></channel><channel id="731"><display-name>Kairali WE TV</display-name></channel><channel id="732"><display-name>9X Tashan</display-name></channel><channel id="733"><display-name>Sun Udaya Comedy</display-name></channel><channel id="734"><display-name>Vissa TV</display-name></channel><channel id="735"><display-name>Sangeet Marathi</display-name></channel><channel id="737"><display-name>Raj Music Telugu</display-name></channel><channel id="739"><display-name>Raj Music Malayalam</display-name></channel><channel id="740"><display-name>Sangeet Bangla</display-name></channel><channel id="741"><display-name>Sangeet Bhojpuri</display-name></channel><channel id="742"><display-name>mh1 (Music)</display-name></channel><channel id="743"><display-name>Raj Music Kannada</display-name></channel><channel id="744"><display-name>Sun Udaya Music</display-name></channel><channel id="747"><display-name>Sun Surya Music</display-name></channel><channel id="748"><display-name>Raj Musix</display-name></channel><channel id="751"><display-name>Tarang Music</display-name></channel><channel id="755"><display-name>Colors Marathi HD</display-name></channel><channel id="756"><display-name>Colors Bangla HD</display-name></channel><channel id="757"><display-name>Colors Kannada HD</display-name></channel><channel id="760"><display-name>Maa Movies HD</display-name></channel><channel id="762"><display-name>Sony Pix HD</display-name></channel><channel id="764"><display-name>Channel News Asia International</display-name></channel><channel id="765"><display-name>Jonack</display-name></channel><channel id="767"><display-name>Raj News 24x7</display-name></channel><channel id="768"><display-name>Jan TV</display-name></channel><channel id="769"><display-name>V6 News</display-name></channel><channel id="770"><display-name>Kashish News</display-name></channel><channel id="771"><display-name>Live Today</display-name></channel><channel id="772"><display-name>CVR OM Spiritual</display-name></channel><channel id="773"><display-name>Public Music</display-name></channel><channel id="774"><display-name>CVR Health</display-name></channel><channel id="775"><display-name>Vanitha</display-name></channel><channel id="776"><display-name>Bhakti TV</display-name></channel><channel id="777"><display-name>Aradhana TV</display-name></channel><channel id="778"><display-name>Public TV</display-name></channel><channel id="779"><display-name>Prameya News 7</display-name></channel><channel id="780"><display-name>Mathrubhumi News</display-name></channel><channel id="781"><display-name>Kalinga TV</display-name></channel><channel id="782"><display-name>Sandesh News</display-name></channel><channel id="783"><display-name>K News India</display-name></channel><channel id="784"><display-name>CVR News</display-name></channel><channel id="785"><display-name>Colors Super</display-name></channel><channel id="786"><display-name>Kappa TV</display-name></channel><channel id="787"><display-name>CVR English</display-name></channel><channel id="788"><display-name>India Voice</display-name></channel><channel id="789"><display-name>JK 24x7 News</display-name></channel><channel id="790"><display-name>I News</display-name></channel><channel id="791"><display-name>Taaza TV</display-name></channel><channel id="792"><display-name>News State UK UP</display-name></channel><channel id="794"><display-name>Peace of Mind</display-name></channel><channel id="795"><display-name>testa</display-name></channel><channel id="796"><display-name>Peppers TV</display-name></channel><channel id="801"><display-name>Divya TV</display-name></channel><channel id="803"><display-name>Tunes 6</display-name></channel><channel id="804"><display-name>Samachar Plus</display-name></channel><channel id="807"><display-name>Gulistan News</display-name></channel><channel id="808"><display-name>Hindi Khabar</display-name></channel><channel id="809"><display-name>Maha Movies</display-name></channel><channel id="810"><display-name>Janam TV</display-name></channel><channel id="814"><display-name>Travelxp Tamil</display-name></channel><channel id="815"><display-name>Sonic Hindi</display-name></channel><channel id="816"><display-name>Cartoon Network Hindi</display-name></channel><channel id="817"><display-name>Cartoon Network Tamil</display-name></channel><channel id="824"><display-name>Puthu Yugam</display-name></channel><channel id="826"><display-name>Malaimurasu Seithigal</display-name></channel><channel id="828"><display-name>Shubh TV</display-name></channel><channel id="829"><display-name>Sri Sankara</display-name></channel><channel id="830"><display-name>Thanthi TV</display-name></channel><channel id="831"><display-name>Living India News</display-name></channel><channel id="832"><display-name>10 TV</display-name></channel><channel id="835"><display-name>Angel TV HD</display-name></channel><channel id="837"><display-name>Euro News</display-name></channel><channel id="838"><display-name>France 24</display-name></channel><channel id="842"><display-name>Jeevan TV</display-name></channel><channel id="843"><display-name>Madhimugam TV</display-name></channel><channel id="844"><display-name>Mazhavil Manorama HD</display-name></channel><channel id="846"><display-name>MKN News</display-name></channel><channel id="850"><display-name>News India 24x7</display-name></channel><channel id="851"><display-name>SMBC TV</display-name></channel><channel id="852"><display-name>Sony BBC Earth HD English</display-name></channel><channel id="855"><display-name>Total TV</display-name></channel><channel id="856"><display-name>Vedic TV</display-name></channel><channel id="857"><display-name>Vendhar TV</display-name></channel><channel id="858"><display-name>Republic TV</display-name></channel><channel id="866"><display-name>Jio Exclusive HD</display-name></channel><channel id="871"><display-name>Jio Events HD</display-name></channel><channel id="872"><display-name>Sony Yay Hindi</display-name></channel><channel id="873"><display-name>Sony Yay Tamil</display-name></channel><channel id="874"><display-name>Sony Yay Telugu</display-name></channel><channel id="875"><display-name>Eurosport HD</display-name></channel><channel id="876"><display-name>Times Now World</display-name></channel><channel id="877"><display-name>MNX HD</display-name></channel><channel id="879"><display-name>Hare krsna</display-name></channel><channel id="880"><display-name>Janta TV</display-name></channel><channel id="882"><display-name>News11</display-name></channel><channel id="883"><display-name>Oscar Movies</display-name></channel><channel id="885"><display-name>TV5 Monde</display-name></channel><channel id="886"><display-name>Lakshya TV</display-name></channel><channel id="887"><display-name>Vedant Ras Swar Shree</display-name></channel><channel id="889"><display-name>Jio Sports HD</display-name></channel><channel id="891"><display-name>Sony Ten 2 HD</display-name></channel><channel id="892"><display-name>Sony Ten 3 HD Hindi</display-name></channel><channel id="894"><display-name>KTV HD</display-name></channel><channel id="895"><display-name>Sun Music HD</display-name></channel><channel id="896"><display-name>Sun TV HD</display-name></channel><channel id="897"><display-name>Sun Gemini HD</display-name></channel><channel id="898"><display-name>Sun Gemini Music HD</display-name></channel><channel id="899"><display-name>Sun Gemini Movies HD</display-name></channel><channel id="900"><display-name>Sun Surya HD</display-name></channel><channel id="901"><display-name>Sun Udaya HD</display-name></channel><channel id="903"><display-name>Only Music</display-name></channel><channel id="904"><display-name>Sanjha TV</display-name></channel><channel id="906"><display-name>Desi Channel</display-name></channel><channel id="907"><display-name>GoodNews Channel</display-name></channel><channel id="908"><display-name>Newslive Bangla</display-name></channel><channel id="910"><display-name>Media One TV</display-name></channel><channel id="915"><display-name>Khabar Fast</display-name></channel><channel id="916"><display-name>TV 100</display-name></channel><channel id="918"><display-name>Bharat Samachar</display-name></channel><channel id="919"><display-name>Anjan TV</display-name></channel><channel id="921"><display-name>Prime News</display-name></channel><channel id="923"><display-name>R.Kannada</display-name></channel><channel id="924"><display-name>Mercy TV</display-name></channel><channel id="927"><display-name>First India News</display-name></channel><channel id="929"><display-name>Zee 24 Kalak</display-name></channel><channel id="931"><display-name>Star Bharat HD</display-name></channel><channel id="933"><display-name>4 TV</display-name></channel><channel id="934"><display-name>Divya Vani</display-name></channel><channel id="936"><display-name>News 1 India</display-name></channel><channel id="937"><display-name>Sai TV</display-name></channel><channel id="939"><display-name>Bhakti Sagar TV</display-name></channel><channel id="944"><display-name>Mantavya News</display-name></channel><channel id="946"><display-name>Pitaara</display-name></channel><channel id="950"><display-name>R Plus</display-name></channel><channel id="951"><display-name>Live Samachar Bharat</display-name></channel><channel id="952"><display-name>Garv Punjabi Gurbani</display-name></channel><channel id="953"><display-name>Propex TV</display-name></channel><channel id="955"><display-name>Hindu Dharmam</display-name></channel><channel id="956"><display-name>TV 5 Kannada</display-name></channel><channel id="957"><display-name>INH 24x7</display-name></channel><channel id="958"><display-name>DNN</display-name></channel><channel id="959"><display-name>JUS PUNJABI HD</display-name></channel><channel id="960"><display-name>JUS HINDI HD</display-name></channel><channel id="961"><display-name>JUS ONE HD</display-name></channel><channel id="962"><display-name>Boogle Bollywood</display-name></channel><channel id="963"><display-name>Arre HD</display-name></channel><channel id="964"><display-name>Om Shanti</display-name></channel><channel id="965"><display-name>News18 Kerala</display-name></channel><channel id="970"><display-name>Win TV</display-name></channel><channel id="971"><display-name>Vaanavil TV</display-name></channel><channel id="972"><display-name>Sarv Dharam Sangam</display-name></channel><channel id="975"><display-name>Jantantra</display-name></channel><channel id="977"><display-name>Calvary</display-name></channel><channel id="978"><display-name>TEST1 HD</display-name></channel><channel id="979"><display-name>TEST2 HD</display-name></channel><channel id="980"><display-name>Swayam Prabha 01</display-name></channel><channel id="981"><display-name>Swayam Prabha 02</display-name></channel><channel id="982"><display-name>Swayam Prabha 03</display-name></channel><channel id="983"><display-name>Swayam Prabha 08</display-name></channel><channel id="984"><display-name>Swayam Prabha 04</display-name></channel><channel id="985"><display-name>Swayam Prabha 07</display-name></channel><channel id="986"><display-name>Swayam Prabha 05</display-name></channel><channel id="987"><display-name>Swayam Prabha 06</display-name></channel><channel id="988"><display-name>Swayam Prabha 09</display-name></channel><channel id="989"><display-name>Swayam Prabha 10</display-name></channel><channel id="990"><display-name>Swayam Prabha 11</display-name></channel><channel id="991"><display-name>Swayam Prabha 12</display-name></channel><channel id="992"><display-name>Swayam Prabha 13</display-name></channel><channel id="993"><display-name>Swayam Prabha 14</display-name></channel><channel id="994"><display-name>Swayam Prabha 16</display-name></channel><channel id="995"><display-name>Swayam Prabha 15</display-name></channel><channel id="996"><display-name>Swayam Prabha 17</display-name></channel><channel id="997"><display-name>Swayam Prabha 21</display-name></channel><channel id="998"><display-name>Swayam Prabha 22</display-name></channel><channel id="999"><display-name>Swayam Prabha 18</display-name></channel><channel id="1059"><display-name>TEST3 HD</display-name></channel><channel id="1061"><display-name>TEST5 HD</display-name></channel><channel id="1069"><display-name>Vande Gujarat 1</display-name></channel><channel id="1070"><display-name>Vande Gujarat 2</display-name></channel><channel id="1071"><display-name>Vande Gujarat 4</display-name></channel><channel id="1075"><display-name>Ayush TV</display-name></channel><channel id="1077"><display-name>Sharnam TV</display-name></channel><channel id="1078"><display-name>Soham TV</display-name></channel><channel id="1079"><display-name>Cartoon Network HD+ English</display-name></channel><channel id="1080"><display-name>Cartoon Network HD+ Telugu</display-name></channel><channel id="1081"><display-name>Cartoon Network HD+ Tamil</display-name></channel><channel id="1082"><display-name>Vande Gujarat 3</display-name></channel><channel id="1083"><display-name>Vande Gujarat 5</display-name></channel><channel id="1084"><display-name>Vande Gujarat 6</display-name></channel><channel id="1085"><display-name>Vande Gujarat 7</display-name></channel><channel id="1086"><display-name>Vande Gujarat 8</display-name></channel><channel id="1087"><display-name>Vande Gujarat 9</display-name></channel><channel id="1088"><display-name>Vande Gujarat 10</display-name></channel><channel id="1089"><display-name>Vande Gujarat 11</display-name></channel><channel id="1090"><display-name>Vande Gujarat 12</display-name></channel><channel id="1091"><display-name>Vande Gujarat 13</display-name></channel><channel id="1092"><display-name>Vande Gujarat 14</display-name></channel><channel id="1093"><display-name>Vande Gujarat 15</display-name></channel><channel id="1094"><display-name>Vande Gujarat 16</display-name></channel><channel id="1102"><display-name>RDX Goa</display-name></channel><channel id="1103"><display-name>PEACE MUSIC</display-name></channel><channel id="1104"><display-name>Star Movies HD</display-name></channel><channel id="1110"><display-name>Star Movies Select HD</display-name></channel><channel id="1112"><display-name>Maa HD</display-name></channel><channel id="1113"><display-name>Star Gold Select HD</display-name></channel><channel id="1120"><display-name>Jalsha Movies</display-name></channel><channel id="1129"><display-name>Maa Music</display-name></channel><channel id="1132"><display-name>Star Plus HD</display-name></channel><channel id="1136"><display-name>Star Utsav Movies</display-name></channel><channel id="1137"><display-name>Maa Gold</display-name></channel><channel id="1139"><display-name>Asianet Plus</display-name></channel><channel id="1140"><display-name>Suvarna Plus</display-name></channel><channel id="1143"><display-name>Star Utsav</display-name></channel><channel id="1145"><display-name>MTV HD</display-name></channel><channel id="1146"><display-name>Sony Marathi SD</display-name></channel><channel id="1148"><display-name>TEST8 HD</display-name></channel><channel id="1158"><display-name>Colors Infinity HD</display-name></channel><channel id="1159"><display-name>Tulja Bhavani</display-name></channel><channel id="1163"><display-name>JioGames HD</display-name></channel><channel id="1170"><display-name>PTC News</display-name></channel><channel id="1171"><display-name>PTC Punjabi</display-name></channel><channel id="1172"><display-name>PTC Chak De</display-name></channel><channel id="1174"><display-name>Fateh TV</display-name></channel><channel id="1175"><display-name>Awakening</display-name></channel><channel id="1179"><display-name>Bansal News</display-name></channel><channel id="1184"><display-name>Steelbird Music</display-name></channel><channel id="1185"><display-name>Swadesh News</display-name></channel><channel id="1186"><display-name>Kartavya TV</display-name></channel><channel id="1187"><display-name>Valam TV</display-name></channel><channel id="1189"><display-name>PTC Music</display-name></channel><channel id="1190"><display-name>PTC Punjabi Gold </display-name></channel><channel id="1191"><display-name>PTC Simran</display-name></channel><channel id="1192"><display-name>Brit Asia</display-name></channel><channel id="1193"><display-name>Hare Krsna Music</display-name></channel><channel id="1205"><display-name>ABP Ganga</display-name></channel><channel id="1209"><display-name>Kalaignar TV</display-name></channel><channel id="1210"><display-name>Kalaignar Seithigal </display-name></channel><channel id="1212"><display-name>Hare Krsna Pravachan</display-name></channel><channel id="1219"><display-name>Animal Planet HD Tamil</display-name></channel><channel id="1220"><display-name>Rajyoga TV</display-name></channel><channel id="1221"><display-name>Rajyoga TV Kannada</display-name></channel><channel id="1223"><display-name>Dagdusheth Ganpati - Pune</display-name></channel><channel id="1224"><display-name>Nimbark TV</display-name></channel><channel id="1226"><display-name>Nick HD+</display-name></channel><channel id="1227"><display-name>Digishala</display-name></channel><channel id="1229"><display-name>TEST9 HD</display-name></channel><channel id="1230"><display-name>PTC VR</display-name></channel><channel id="1232"><display-name>Hi Dost!</display-name></channel><channel id="1240"><display-name>TEST10 HD</display-name></channel><channel id="1242"><display-name>Sonic Telugu</display-name></channel><channel id="1243"><display-name>Sonic Kannada</display-name></channel><channel id="1244"><display-name>Nick Kannada</display-name></channel><channel id="1246"><display-name>Headlines Tripura</display-name></channel><channel id="1250"><display-name>Twenty Four News</display-name></channel><channel id="1251"><display-name>TV9 Bharatvarsh</display-name></channel><channel id="1252"><display-name>Tehzeeb TV</display-name></channel><channel id="1254"><display-name>Aastha Telugu</display-name></channel><channel id="1255"><display-name>Aastha Gujarati</display-name></channel><channel id="1256"><display-name>Aastha Kannada</display-name></channel><channel id="1257"><display-name>Surya Samachar</display-name></channel><channel id="1260"><display-name>Ctvn Akd Plus</display-name></channel><channel id="1261"><display-name>Calcutta News</display-name></channel><channel id="1263"><display-name>BRK News</display-name></channel><channel id="1264"><display-name>Kolkata TV</display-name></channel><channel id="1265"><display-name>Global Sanjh</display-name></channel><channel id="1273"><display-name>Gomantak TV</display-name></channel><channel id="1274"><display-name>Studio One</display-name></channel><channel id="1278"><display-name>Prarthana Bhawan</display-name></channel><channel id="1284"><display-name>Vignesh TV</display-name></channel><channel id="1286"><display-name>Insync</display-name></channel><channel id="1287"><display-name>ANB News</display-name></channel><channel id="1291"><display-name>ABP Sanjha</display-name></channel><channel id="1293"><display-name>Lokshahi News</display-name></channel><channel id="1294"><display-name>Eurosport</display-name></channel><channel id="1295"><display-name>B4U Kadak</display-name></channel><channel id="1296"><display-name>B4U Bhojpuri</display-name></channel><channel id="1315"><display-name>HHDL</display-name></channel><channel id="1324"><display-name>Colors Gujarati Cinema</display-name></channel><channel id="1325"><display-name>Colors Infinity SD</display-name></channel><channel id="1326"><display-name>Colors Marathi SD</display-name></channel><channel id="1328"><display-name>DD Arunprabha</display-name></channel><channel id="1329"><display-name>DD Gyandarshan</display-name></channel><channel id="1332"><display-name>Nat Geo Wild HD</display-name></channel><channel id="1335"><display-name>National Geographic HD</display-name></channel><channel id="1338"><display-name>RT India</display-name></channel><channel id="1340"><display-name>Nick Malayalam</display-name></channel><channel id="1341"><display-name>Nick Bangla</display-name></channel><channel id="1342"><display-name>Nick Marathi</display-name></channel><channel id="1344"><display-name>Sonic Malayalam</display-name></channel><channel id="1345"><display-name>Sonic Bangla</display-name></channel><channel id="1346"><display-name>Sonic Marathi</display-name></channel><channel id="1368"><display-name>Colors SD</display-name></channel><channel id="1369"><display-name>Colors Bangla SD</display-name></channel><channel id="1370"><display-name>Colors Kannada SD</display-name></channel><channel id="1371"><display-name>Colors Tamil</display-name></channel><channel id="1373"><display-name>Disney Channel</display-name></channel><channel id="1374"><display-name>Disney Junior</display-name></channel><channel id="1375"><display-name>Disney International HD</display-name></channel><channel id="1388"><display-name>Goodness</display-name></channel><channel id="1391"><display-name>Hungama</display-name></channel><channel id="1392"><display-name>Super Hungama</display-name></channel><channel id="1393"><display-name>Sony Wah</display-name></channel><channel id="1394"><display-name>Jai Maharashtra</display-name></channel><channel id="1396"><display-name>Set SD</display-name></channel><channel id="1401"><display-name>Romedy Now</display-name></channel><channel id="1403"><display-name>Republic Bharat</display-name></channel><channel id="1405"><display-name>NHK World Japan</display-name></channel><channel id="1407"><display-name>Sai Leela</display-name></channel><channel id="1408"><display-name>Reporter TV</display-name></channel><channel id="1410"><display-name>PM e Vidya 11</display-name></channel><channel id="1411"><display-name>SongDew TV</display-name></channel><channel id="1414"><display-name>Prati Shirdi Saibaba</display-name></channel><channel id="1415"><display-name>Ganga Darshan Varanasi</display-name></channel><channel id="1417"><display-name>SVBC2</display-name></channel><channel id="1418"><display-name>Ichhapuran Balaji Rajasthan</display-name></channel><channel id="1426"><display-name>Santvani</display-name></channel><channel id="1427"><display-name>Nandighosha</display-name></channel><channel id="1429"><display-name>KITE VICTERS</display-name></channel><channel id="1431"><display-name>BBC News Hindi</display-name></channel><channel id="1432"><display-name>TIME8</display-name></channel><channel id="1433"><display-name>India Science</display-name></channel><channel id="1440"><display-name>Krishna Vani</display-name></channel><channel id="1441"><display-name>Wah Punjabi</display-name></channel><channel id="1450"><display-name>Colors Cineplex Superhit</display-name></channel><channel id="1452"><display-name>Shemaroo MarathiBana</display-name></channel><channel id="1453"><display-name>Balle Balle TV</display-name></channel><channel id="1454"><display-name>Shiksha TV</display-name></channel><channel id="1455"><display-name>Janapriyam</display-name></channel><channel id="1457"><display-name>News Only</display-name></channel><channel id="1458"><display-name>Gurkibani</display-name></channel><channel id="1471"><display-name>History TV18</display-name></channel><channel id="1475"><display-name>TEST11 HD</display-name></channel><channel id="1476"><display-name>TEST12 HD</display-name></channel><channel id="1477"><display-name>Colors Cineplex HD</display-name></channel><channel id="1481"><display-name>Argus News</display-name></channel><channel id="1494"><display-name>BHOOMI 24x7</display-name></channel><channel id="1514"><display-name>Kannur One</display-name></channel><channel id="1515"><display-name>News J</display-name></channel><channel id="1516"><display-name>DD Yadagiri</display-name></channel><channel id="1518"><display-name>Moon TV</display-name></channel><channel id="1521"><display-name>Birla Brainiacs</display-name></channel><channel id="1525"><display-name>TEST13 HD</display-name></channel><channel id="1527"><display-name>Haryanvi Hits</display-name></channel><channel id="1528"><display-name>Network 10</display-name></channel><channel id="1529"><display-name>MI TV</display-name></channel><channel id="1531"><display-name>Gyanvani 1</display-name></channel><channel id="1532"><display-name>PM e Vidya 12</display-name></channel><channel id="1537"><display-name>RadheKrishna TV</display-name></channel><channel id="1538"><display-name>Samachar Today</display-name></channel><channel id="1543"><display-name>Subharti</display-name></channel><channel id="1545"><display-name>Punjab School TV</display-name></channel><channel id="1549"><display-name>Dharm Granth TV</display-name></channel><channel id="1550"><display-name>AB News</display-name></channel><channel id="1551"><display-name>P News</display-name></channel><channel id="1552"><display-name>Malanadu TV</display-name></channel><channel id="1553"><display-name>AB Star News</display-name></channel><channel id="1554"><display-name>Sanatan TV</display-name></channel><channel id="1555"><display-name>News First</display-name></channel><channel id="1560"><display-name>35mm</display-name></channel><channel id="1561"><display-name>Sristi TV</display-name></channel><channel id="1568"><display-name>Atmadarshan TV</display-name></channel><channel id="1594"><display-name>Samachar 24</display-name></channel><channel id="1598"><display-name>FTV HD</display-name></channel><channel id="1605"><display-name>Bangla Bhakti</display-name></channel><channel id="1607"><display-name>Manav Dharam</display-name></channel><channel id="1608"><display-name>MP News</display-name></channel><channel id="1610"><display-name>Divyang News</display-name></channel><channel id="1612"><display-name>Tara TV</display-name></channel><channel id="1618"><display-name>Real News Kerala</display-name></channel><channel id="1632"><display-name>Colors Kannada Cinema</display-name></channel><channel id="1633"><display-name>Public Movies</display-name></channel><channel id="1634"><display-name>Siri Kannada</display-name></channel><channel id="1635"><display-name>News State MPCG </display-name></channel><channel id="1643"><display-name>Harvest TV 24x7</display-name></channel><channel id="1644"><display-name>Powervision TV</display-name></channel><channel id="1647"><display-name>MK Six</display-name></channel><channel id="1655"><display-name>Madha TV</display-name></channel><channel id="1657"><display-name>Colors Bangla Cinema</display-name></channel><channel id="1662"><display-name>Sun Surya Comedy</display-name></channel><channel id="1665"><display-name>ETV Cinema HD </display-name></channel><channel id="1666"><display-name>Safari TV </display-name></channel><channel id="1667"><display-name>Rongeen TV</display-name></channel><channel id="1669"><display-name>Sun Bangla</display-name></channel><channel id="1670"><display-name>C News Bharat</display-name></channel><channel id="1690"><display-name>BVTV</display-name></channel><channel id="1692"><display-name>Badakhabar</display-name></channel><channel id="1694"><display-name>Haryana Beats</display-name></channel><channel id="1695"><display-name>Prime TV</display-name></channel><channel id="1697"><display-name>FM News</display-name></channel><channel id="1698"><display-name>IND 24</display-name></channel><channel id="1699"><display-name>ANN News</display-name></channel><channel id="1705"><display-name>Shri Hingulambika Devi Temple</display-name></channel><channel id="1706"><display-name>Shri Mangal Dev Grah Temple</display-name></channel><channel id="1725"><display-name>24Hrs TV</display-name></channel><channel id="1728"><display-name>Anaadi TV</display-name></channel><channel id="1733"><display-name>ND 24</display-name></channel><channel id="1735"><display-name>TV9 Bangla</display-name></channel><channel id="1736"><display-name>LUXE TV</display-name></channel><channel id="1738"><display-name>Hosanna TV</display-name></channel><channel id="1740"><display-name>Purnima TV</display-name></channel><channel id="1741"><display-name>Bharat AtoZ</display-name></channel><channel id="1742"><display-name>Sanskrit Ganga</display-name></channel><channel id="1743"><display-name>Hornbill TV</display-name></channel><channel id="1747"><display-name>India News Gujarat</display-name></channel><channel id="1754"><display-name>Sun Surya Movies</display-name></channel><channel id="1757"><display-name>NK TV Plus</display-name></channel><channel id="1759"><display-name>Buletin India</display-name></channel><channel id="1761"><display-name>Aryan TV National</display-name></channel><channel id="1762"><display-name>Channel Vision</display-name></channel><channel id="1763"><display-name>Colors Cineplex Bollywood</display-name></channel><channel id="1764"><display-name>Dada Bhagwan Foundation</display-name></channel><channel id="1771"><display-name>Express News</display-name></channel><channel id="1774"><display-name>Sony Ten 4 Tamil</display-name></channel><channel id="1775"><display-name>Sony Ten 4 Telugu</display-name></channel><channel id="1777"><display-name>Bharat News TV</display-name></channel><channel id="1780"><display-name>HooplaKidz TV</display-name></channel><channel id="1789"><display-name>Dada Bhagwan Foundation Gujarati</display-name></channel><channel id="1790"><display-name>VR Live</display-name></channel><channel id="1793"><display-name>National News Sattaxpress</display-name></channel><channel id="1794"><display-name>Mangalmay Live</display-name></channel><channel id="1795"><display-name>Shri Amarnathji Shrine Board</display-name></channel><channel id="1796"><display-name>Ananda Barta</display-name></channel><channel id="1797"><display-name>DA News Plus</display-name></channel><channel id="1798"><display-name>Pasand</display-name></channel><channel id="1799"><display-name>Studio Yuva Alpha</display-name></channel><channel id="1804"><display-name>Jan Setu News</display-name></channel><channel id="1817"><display-name>NEWS 24 MPCG</display-name></channel><channel id="1826"><display-name>Swaralasika Sangeetalaya</display-name></channel><channel id="1834"><display-name>Green Chillies</display-name></channel><channel id="1847"><display-name>Z10 TV</display-name></channel><channel id="1850"><display-name>SVBC</display-name></channel><channel id="1853"><display-name>News11 Bharat</display-name></channel><channel id="1854"><display-name>STV Haryana News</display-name></channel><channel id="1855"><display-name>NL TV</display-name></channel><channel id="1856"><display-name>Pratham Khabar 24x7</display-name></channel><channel id="1858"><display-name>SVBC3</display-name></channel><channel id="1859"><display-name>SVBC4</display-name></channel><channel id="1868"><display-name>Punjab Plus</display-name></channel><channel id="1871"><display-name>7X Music</display-name></channel><channel id="1883"><display-name>Pogo Telugu</display-name></channel><channel id="1885"><display-name>Kripa TV</display-name></channel><channel id="1886"><display-name>Sansad TV Rajya Sabha</display-name></channel><channel id="1891"><display-name>KTV Bangla</display-name></channel><channel id="1895"><display-name>Today 24 News</display-name></channel><channel id="1896"><display-name>News Flash</display-name></channel><channel id="1897"><display-name>Pulse 24</display-name></channel><channel id="1898"><display-name>GBN24</display-name></channel><channel id="1900"><display-name>Express News Bharat</display-name></channel><channel id="1901"><display-name>Adhyatma TV</display-name></channel><channel id="1906"><display-name>Times Now Navbharat</display-name></channel><channel id="1907"><display-name>ET Now Swadesh</display-name></channel><channel id="1925"><display-name>MH1 Dil Se</display-name></channel><channel id="1954"><display-name>News Tamil 24x7</display-name></channel><channel id="1955"><display-name>Foodxp</display-name></channel><channel id="1956"><display-name>Sidharth TV</display-name></channel><channel id="1957"><display-name>Sidharth Gold</display-name></channel><channel id="1958"><display-name>Sidharth Bhakti</display-name></channel><channel id="1959"><display-name>Global India</display-name></channel><channel id="1961"><display-name>Shemaroo TV</display-name></channel><channel id="1962"><display-name>Amar Bangla TV</display-name></channel><channel id="1964"><display-name>ABC News</display-name></channel><channel id="1965"><display-name>VNM TV</display-name></channel><channel id="1967"><display-name>PMC Hindi</display-name></channel><channel id="1972"><display-name>Top News Marathi</display-name></channel><channel id="1973"><display-name>ETV HD</display-name></channel><channel id="1974"><display-name>Gujarat 1st 24x7</display-name></channel><channel id="1975"><display-name>PMC Telugu</display-name></channel><channel id="1999"><display-name>Raftaar Media</display-name></channel><channel id="2002"><display-name>Aadinath TV</display-name></channel><channel id="2003"><display-name>3.0 TV</display-name></channel><channel id="2004"><display-name>Shekinah TV</display-name></channel><channel id="2005"><display-name>IN 24 News</display-name></channel><channel id="2007"><display-name>BS9 News</display-name></channel><channel id="2008"><display-name>News 21</display-name></channel><channel id="2014"><display-name>News India TV</display-name></channel><channel id="2017"><display-name>Munsif TV</display-name></channel><channel id="2018"><display-name>Samachar Nation</display-name></channel><channel id="2019"><display-name>Global Punjab</display-name></channel><channel id="2020"><display-name>KKD News</display-name></channel><channel id="2021"><display-name>HNN 24x7</display-name></channel><channel id="2022"><display-name>Asom Live 24</display-name></channel><channel id="2027"><display-name>Raatdin Bangla</display-name></channel><channel id="2028"><display-name>Sadvidya TV</display-name></channel><channel id="2029"><display-name>Aaryaa Bhakti</display-name></channel><channel id="2030"><display-name>Aaryaa News</display-name></channel><channel id="2031"><display-name>Fashion India</display-name></channel><channel id="2063"><display-name>RS Bharat</display-name></channel><channel id="2064"><display-name>Merchant Records</display-name></channel><channel id="2077"><display-name>Gangaur</display-name></channel><channel id="2078"><display-name>Shemaroo Umang</display-name></channel><channel id="2079"><display-name>Bharat 24</display-name></channel><channel id="2081"><display-name>TV27 News</display-name></channel><channel id="2082"><display-name>22Scope News</display-name></channel><channel id="2176"><display-name>India 24x7</display-name></channel><channel id="2184"><display-name>U Bangla</display-name></channel><channel id="2187"><display-name>Swatantra News</display-name></channel><channel id="2188"><display-name>Globe TV</display-name></channel><channel id="2189"><display-name>Aaryaa Cinema</display-name></channel><channel id="2192"><display-name>Gurukul</display-name></channel><channel id="2224"><display-name>India News Punjab</display-name></channel><channel id="2225"><display-name>TV24</display-name></channel><channel id="2228"><display-name>Samay Kolkata</display-name></channel><channel id="2229"><display-name>Bhojpuri Junction</display-name></channel><channel id="2230"><display-name>Jio Specials HD</display-name></channel><channel id="2252"><display-name>Desi Music Station</display-name></channel><channel id="2253"><display-name>Nakshatra Digital TV</display-name></channel><channel id="2254"><display-name>Media9</display-name></channel><channel id="2255"><display-name>Raftaar Samay</display-name></channel><channel id="2258"><display-name>Animax</display-name></channel><channel id="2322"><display-name>Divyalok TV</display-name></channel><channel id="2323"><display-name>TTN24</display-name></channel><channel id="2325"><display-name>Punjabi Melodies</display-name></channel><channel id="2326"><display-name>Firstpost</display-name></channel><channel id="2327"><display-name>Lionsgate Play</display-name></channel><channel id="2328"><display-name>CyberPeace TV</display-name></channel><channel id="2352"><display-name>Narikaa</display-name></channel><channel id="2353"><display-name>Bharat Express</display-name></channel><channel id="2354"><display-name>Friends TV</display-name></channel><channel id="2423"><display-name>Vande Bharat News</display-name></channel><channel id="2424"><display-name>Sun Marathi</display-name></channel><channel id="2433"><display-name>E News79</display-name></channel><channel id="2434"><display-name>M Nadu</display-name></channel><channel id="2435"><display-name>Spondon</display-name></channel><channel id="2436"><display-name>Prime 9 News</display-name></channel><channel id="2437"><display-name>Wild Earth</display-name></channel><channel id="2742"><display-name>Zee Kannada News</display-name></channel><channel id="2743"><display-name>Power TV</display-name></channel><channel id="2750"><display-name>Saga Music</display-name></channel><channel id="2751"><display-name>Saga Music Haryanvi</display-name></channel><channel id="2752"><display-name>Ghaint Punjab</display-name></channel><channel id="2753"><display-name>YRF Music</display-name></channel><channel id="2754"><display-name>Sikh Ratnavali</display-name></channel><channel id="2759"><display-name>DD North East</display-name></channel><channel id="2764"><display-name>News State Bihar Jharkhand</display-name></channel><channel id="2765"><display-name>BSTV</display-name></channel><channel id="2766"><display-name>BRAVE TV</display-name></channel><channel id="2767"><display-name>Sacchi Report</display-name></channel><channel id="2768"><display-name>Jothi TV</display-name></channel><channel id="2770"><display-name>Har Khabar</display-name></channel><channel id="2771"><display-name>Sadhna News MP CG</display-name></channel><channel id="2772"><display-name>India Daily 24x7</display-name></channel><channel id="2773"><display-name>Aaj Ki Khabar</display-name></channel><channel id="2774"><display-name>Power Kids TV</display-name></channel><channel id="2775"><display-name>Grace TV</display-name></channel><channel id="2777"><display-name>Asian News</display-name></channel><channel id="2778"><display-name>Tabbar Hits</display-name></channel><channel id="2779"><display-name>Red Bull TV</display-name></channel><channel id="2780"><display-name>R Bangla</display-name></channel><channel id="2782"><display-name>ABC Australia</display-name></channel><channel id="2783"><display-name>Big TV</display-name></channel><channel id="2784"><display-name>ISKCON Bangalore</display-name></channel><channel id="2817"><display-name>Boogle Bangla</display-name></channel><channel id="2851"><display-name>IN24 Live</display-name></channel><channel id="2854"><display-name>KCM</display-name></channel><channel id="2862"><display-name>Mahaa News</display-name></channel><channel id="2914"><display-name>BHI Channel</display-name></channel><channel id="2916"><display-name>Daily Post PHH</display-name></channel><channel id="2917"><display-name>Sadhna Gold</display-name></channel><channel id="2918"><display-name>WPN World Punjabi News</display-name></channel><channel id="2932"><display-name>99 TV</display-name></channel><channel id="2933"><display-name>NK TV Bangla</display-name></channel><channel id="2934"><display-name>Punjabi Hits</display-name></channel><channel id="2935"><display-name>Pudhari News</display-name></channel><channel id="2936"><display-name>Oye Music</display-name></channel><channel id="2937"><display-name>Update India</display-name></channel><channel id="2945"><display-name>Tar TV</display-name></channel><channel id="2946"><display-name>National News</display-name></channel><channel id="2947"><display-name>Jeewan Bhakti</display-name></channel><channel id="2954"><display-name>TV45</display-name></channel><channel id="2956"><display-name>ETV Plus HD</display-name></channel><channel id="2957"><display-name>Public First</display-name></channel><channel id="2958"><display-name>Tamilan Television</display-name></channel><channel id="2962"><display-name>NoFilterNeha</display-name></channel><channel id="3004"><display-name>Velicham Tv</display-name></channel><channel id="3005"><display-name>Rupashi Bangla</display-name></channel><channel id="3006"><display-name>Dhoom Music Bangla</display-name></channel><channel id="3007"><display-name>AMV</display-name></channel><channel id="3008"><display-name>Maya Tv</display-name></channel><channel id="3011"><display-name>Lancs TV HD</display-name></channel><channel id="3014"><display-name>IPN News</display-name></channel><channel id="3016"><display-name>TNI24</display-name></channel><channel id="3017"><display-name>News Hour</display-name></channel><channel id="3018"><display-name>News 360</display-name></channel><channel id="3019"><display-name>Bangla Jago</display-name></channel><channel id="3022"><display-name>Unique TV</display-name></channel><channel id="3023"><display-name>Janadesh News</display-name></channel><channel id="3024"><display-name>India TV Yoga Channel</display-name></channel><channel id="3025"><display-name>India TV Aap Ki Adalat</display-name></channel><channel id="3026"><display-name>India TV Speed News</display-name></channel><channel id="3028"><display-name>BH OTT India Fest</display-name></channel><channel id="3029"><display-name>Bollywood Masala</display-name></channel><channel id="3031"><display-name>Zee Telugu News</display-name></channel><channel id="3032"><display-name>Pogo Kannada</display-name></channel><channel id="3033"><display-name>Pogo Malayalam</display-name></channel><channel id="3034"><display-name>Pogo Marathi</display-name></channel><channel id="3035"><display-name>Cartoon Network Kannada</display-name></channel><channel id="3036"><display-name>Cartoon Network Malayalam</display-name></channel><channel id="3037"><display-name>Kalyan TV</display-name></channel><channel id="3038"><display-name>Amritwani TV</display-name></channel><channel id="3039"><display-name>Garvi Gujarat</display-name></channel><channel id="3041"><display-name>Bharat TV24</display-name></channel><channel id="3042"><display-name>News 24x7</display-name></channel><channel id="3043"><display-name>Prime Asia HD</display-name></channel><channel id="3045"><display-name>Tamil Janam</display-name></channel><channel id="3048"><display-name>BVG</display-name></channel><channel id="3049"><display-name>TNI Awaaz</display-name></channel><channel id="3050"><display-name>Indian News</display-name></channel><channel id="3053"><display-name>TNP News</display-name></channel><channel id="3058"><display-name>News Capital Gujarat</display-name></channel><channel id="3059"><display-name>Thanthi One</display-name></channel><channel id="3060"><display-name>Hiff Movies</display-name></channel><channel id="3063"><display-name>PR News</display-name></channel><channel id="3064"><display-name>Navsarjan Sanskruti News</display-name></channel><channel id="3065"><display-name>Bharat Nation</display-name></channel><channel id="3066"><display-name>Today 24 News UPUK</display-name></channel><channel id="3068"><display-name>Bharat Update</display-name></channel><channel id="3069"><display-name>Captain</display-name></channel><channel id="3070"><display-name>Vistaar News</display-name></channel><channel id="3074"><display-name>Shemaroo Filmy Gaane</display-name></channel><channel id="3075"><display-name>Shemaroo Bollywood</display-name></channel><channel id="3083"><display-name>Sundrani TV</display-name></channel><channel id="3084"><display-name>Taiwan Plus</display-name></channel><channel id="3085"><display-name>SACH BEDHADAK</display-name></channel><channel id="3086"><display-name>Naxatra News Hindi</display-name></channel><channel id="3087"><display-name>Sai TV Telugu</display-name></channel><channel id="3088"><display-name>Sun Neo HD</display-name></channel><channel id="3090"><display-name>KBC News</display-name></channel><channel id="3095"><display-name>NDTV Marathi</display-name></channel><channel id="3096"><display-name>Star Gold 2 HD</display-name></channel><channel id="3097"><display-name>Star Gold Romance</display-name></channel><channel id="3098"><display-name>Star Gold Thrills</display-name></channel><channel id="3100"><display-name>Star Pravah Picture HD</display-name></channel><channel id="3104"><display-name>Smriti Patra TV</display-name></channel><channel id="3105"><display-name>National Tv India</display-name></channel><channel id="3107"><display-name>Bhakthi Siri </display-name></channel><channel id="3108"><display-name>Garvi Gujarat Gujarati</display-name></channel><channel id="3110"><display-name>SB News 24x7</display-name></channel><channel id="3111"><display-name>ATV India News</display-name></channel><channel id="3113"><display-name>Jk Samachar News 24x7</display-name></channel><channel id="3115"><display-name>Jay Jagannath</display-name></channel><channel id="3117"><display-name>Rajya 24 News</display-name></channel><channel id="3118"><display-name>DD Swayam Prabha 23</display-name></channel><channel id="3119"><display-name>DD Swayam Prabha 24</display-name></channel><channel id="3120"><display-name>DD Swayam Prabha 25</display-name></channel><channel id="3121"><display-name>DD Swayam Prabha 26</display-name></channel><channel id="3122"><display-name>DD Swayam Prabha 27</display-name></channel><channel id="3123"><display-name>DD Swayam Prabha 28</display-name></channel><channel id="3124"><display-name>DD Swayam Prabha 29</display-name></channel><channel id="3125"><display-name>DD Swayam Prabha 30</display-name></channel><channel id="3126"><display-name>DD Swayam Prabha 31</display-name></channel><channel id="3127"><display-name>DD Swayam Prabha 32</display-name></channel><channel id="3128"><display-name>DD Swayam Prabha 33</display-name></channel><channel id="3129"><display-name>DD Swayam Prabha 34</display-name></channel><channel id="3130"><display-name>DD Swayam Prabha 35</display-name></channel><channel id="3131"><display-name>DD Swayam Prabha 36</display-name></channel><channel id="3132"><display-name>DD Swayam Prabha 37</display-name></channel><channel id="3133"><display-name>DD Swayam Prabha 38</display-name></channel><channel id="3134"><display-name>DD Swayam Prabha 39</display-name></channel><channel id="3135"><display-name>DD Swayam Prabha 40</display-name></channel><channel id="3136"><display-name>DD Sathee 1</display-name></channel><channel id="3137"><display-name>DD Sathee 2</display-name></channel><channel id="3138"><display-name>DD Sathee 3</display-name></channel><channel id="3139"><display-name>DD Sathee 4</display-name></channel><channel id="3140"><display-name>DD Sathee 5</display-name></channel><channel id="3141"><display-name>DD Sathee 6</display-name></channel><channel id="3142"><display-name>DD Sathee 7</display-name></channel><channel id="3143"><display-name>Mahaa Max</display-name></channel><channel id="3145"><display-name>DD Sathee 8</display-name></channel><channel id="3146"><display-name>All Women&#39;s Sports Network</display-name></channel><channel id="3152"><display-name>News State Punjab Haryana Himachal</display-name></channel><channel id="3154"><display-name>Bloomberg Originals</display-name></channel><channel id="3155"><display-name>Bloomberg TV+</display-name></channel><channel id="3162"><display-name>Prabhu Vani Tv</display-name></channel><channel id="3163"><display-name>Khabar 24x7 News</display-name></channel><channel id="3164"><display-name>Shri News</display-name></channel><channel id="3166"><display-name>Live Times</display-name></channel><channel id="3167"><display-name>Lok manch Marathi</display-name></channel><channel id="3168"><display-name>Sky India Tv</display-name></channel><channel id="3170"><display-name>News 24 Tass</display-name></channel><channel id="3171"><display-name>Khabar 70</display-name></channel><channel id="3172"><display-name>India 24x7 Aap Tak TV</display-name></channel><channel id="3174"><display-name>Malyalam Naaptol</display-name></channel><channel id="3175"><display-name>Tamil Naaptol</display-name></channel><channel id="3176"><display-name>Telugu Naaptol</display-name></channel><channel id="3177"><display-name>Adhya Bhakti</display-name></channel><channel id="3178"><display-name>Ishwar Vani Tv</display-name></channel><channel id="3179"><display-name>News Marathi 24x7</display-name></channel><channel id="3181"><display-name>News Nation 81</display-name></channel><channel id="3182"><display-name>Animal Planet HD Telugu</display-name></channel><channel id="3183"><display-name>Animal Planet Telugu</display-name></channel><channel id="3184"><display-name>News Malayalam</display-name></channel><channel id="3185"><display-name>Kolkata News</display-name></channel><channel id="3186"><display-name>Public Asia</display-name></channel><channel id="3187"><display-name>Prabhu Sandesh</display-name></channel><channel id="3188"><display-name>Shesh Khabar</display-name></channel><channel id="3189"><display-name>Chanakya News India Rajasthan</display-name></channel><channel id="3190"><display-name>Chanakya News National</display-name></channel><channel id="3191"><display-name>S Bharat</display-name></channel><channel id="3192"><display-name>AOne News</display-name></channel><channel id="3197"><display-name>Patnagar Network News</display-name></channel><channel id="3201"><display-name>Sana TV</display-name></channel><channel id="3203"><display-name>Nation Khabar</display-name></channel><channel id="3204"><display-name>Penta TV</display-name></channel><channel id="3213"><display-name>Gusto TV</display-name></channel><channel id="3214"><display-name>Vertent Samachar Plus 24x7</display-name></channel><channel id="3216"><display-name>Krishi Pitaara</display-name></channel><channel id="3217"><display-name>NE News</display-name></channel><channel id="3218"><display-name>STV24 News</display-name></channel><channel id="3219"><display-name>Prajatantra TV Bharat</display-name></channel><channel id="3220"><display-name>Prime Bharat News</display-name></channel><channel id="3221"><display-name>Sri Naga Sai Mandir</display-name></channel><channel id="3223"><display-name>Shark Tank India S5</display-name></channel><channel id="3226"><display-name>R Hindustan Tv News</display-name></channel><channel id="3227"><display-name>Today India News</display-name></channel><channel id="3230"><display-name>Apex News India</display-name></channel><channel id="3231"><display-name>Apex Entertainment</display-name></channel><channel id="3232"><display-name>Sadhguru Television Dolby</display-name></channel><channel id="3234"><display-name>Chanakya News Jharkhand</display-name></channel><channel id="3235"><display-name>Chanakya News UPUK</display-name></channel><channel id="3236"><display-name>Bhakti Dhara</display-name></channel><channel id="3237"><display-name>Namma Bangalore</display-name></channel><channel id="3238"><display-name>Yoga for Beginners</display-name></channel><channel id="3239"><display-name>Mahaa Bhakthi</display-name></channel><channel id="3240"><display-name>News X World</display-name></channel><channel id="3242"><display-name>BHP News</display-name></channel><channel id="3243"><display-name>Pickleball Now</display-name></channel><channel id="3244"><display-name>Sanatan Bharat</display-name></channel><channel id="3247"><display-name>Manage Stress</display-name></channel><channel id="3248"><display-name>Weight Loss Yoga</display-name></channel><channel id="3249"><display-name>Guided Meditation</display-name></channel><channel id="3250"><display-name>Flexibility Yoga</display-name></channel><channel id="3251"><display-name>Restful Sleep</display-name></channel><channel id="3252"><display-name>Muscle Strength</display-name></channel><channel id="3253"><display-name>The Unmute</display-name></channel><channel id="3255"><display-name>Voice TV Urdu</display-name></channel><channel id="3258"><display-name>ATN Samachar</display-name></channel><channel id="3259"><display-name>Pocket Films</display-name></channel><channel id="3260"><display-name>Sanatan Sandesh TV</display-name></channel><channel id="3261"><display-name>Samrat News TV</display-name></channel><channel id="3265"><display-name>Nation World News</display-name></channel><channel id="3266"><display-name>Vijay Super HD</display-name></channel><channel id="3267"><display-name>Star Kiran</display-name></channel><channel id="3268"><display-name>Nation NE</display-name></channel><channel id="3269"><display-name>Vijay Takkar</display-name></channel><channel id="3279"><display-name>OM TV</display-name></channel><channel id="3280"><display-name>Soochna India</display-name></channel><channel id="3281"><display-name>Mahua Play</display-name></channel><channel id="3282"><display-name>Mahua Khabar</display-name></channel><channel id="3283"><display-name>VACC 24 News</display-name></channel><channel id="3284"><display-name>Rozana Spokesman 24x7</display-name></channel><channel id="3285"><display-name>Stingray Naturescape</display-name></channel><channel id="3286"><display-name>ZenLIFE by Stingray</display-name></channel><channel id="3287"><display-name>Holidaycapes by Stingray</display-name></channel><channel id="3288"><display-name>Movie Music by Stingray</display-name></channel><channel id="3289"><display-name>Qello Concerts by Stingray</display-name></channel><channel id="3290"><display-name>Stingray Djazz</display-name></channel><channel id="3291"><display-name>NBC24 News</display-name></channel><channel id="3292"><display-name>NBS Live TV</display-name></channel><channel id="3294"><display-name>Anand TV</display-name></channel><channel id="3295"><display-name>Mahotsav TV </display-name></channel><channel id="3297"><display-name>Amar Digital TV</display-name></channel><channel id="3298"><display-name>Mon TV Bangla</display-name></channel><channel id="3299"><display-name>News_Plus_24x7</display-name></channel><channel id="3300"><display-name>R TV Bhakthi</display-name></channel><channel id="3302"><display-name>T SAT Nipuna</display-name></channel><channel id="3304"><display-name>T SAT Vidya</display-name></channel><channel id="3310"><display-name>MNS News</display-name></channel><channel id="3312"><display-name>Gj Desi News</display-name></channel><channel id="3313"><display-name>LOVEWORLD TV</display-name></channel><channel id="3314"><display-name>Gujarat  Wild TV</display-name></channel><channel id="3317"><display-name>Zillar Barta</display-name></channel><channel id="3319"><display-name>ZB Music</display-name></channel><channel id="3320"><display-name>ZB Bhakti</display-name></channel><channel id="3321"><display-name>ZB Cartoon</display-name></channel><channel id="3322"><display-name>ZB Cinema </display-name></channel><channel id="3323"><display-name>Stingray The Spa</display-name></channel><channel id="3324"><display-name>Stingray Todays K-Pop</display-name></channel><channel id="3325"><display-name>Stingray Easy Listening</display-name></channel><channel id="3327"><display-name>Stingray 2000s</display-name></channel><channel id="3328"><display-name>Aagaaz Times</display-name></channel><channel id="3329"><display-name>Mirror Media</display-name></channel><channel id="3330"><display-name>Ten News</display-name></channel><channel id="3331"><display-name>STV Bangla</display-name></channel><channel id="3332"><display-name>Awaaz India TV</display-name></channel><channel id="3333"><display-name>Popli Live</display-name></channel><channel id="3334"><display-name>Sanatan Vedic TV</display-name></channel><channel id="3336"><display-name>NH BollyFlix</display-name></channel><channel id="3338"><display-name>NH BollyGold</display-name></channel><channel id="3343"><display-name>NH BollyRaga</display-name></channel><channel id="3345"><display-name>Superfine Films</display-name></channel><channel id="3346"><display-name>Yahoo Finance</display-name></channel><channel id="3352"><display-name>Janataa TV Kannada</display-name></channel><channel id="3353"><display-name>NE Bharat24</display-name></channel><channel id="3354"><display-name>Fast1</display-name></channel><channel id="3356"><display-name>Rock TV</display-name></channel><channel id="3357"><display-name>Dharsan TV</display-name></channel><channel id="3358"><display-name>Bhagyam TV</display-name></channel><channel id="3359"><display-name>Sana Plus</display-name></channel><channel id="3360"><display-name>Subin TV</display-name></channel><channel id="3361"><display-name>Shri Shyam TV </display-name></channel><channel id="3365"><display-name>Newz Room Gujarat</display-name></channel><channel id="3366"><display-name>Godlywood Studios</display-name></channel><channel id="3367"><display-name>Mega9TV</display-name></channel><channel id="3368"><display-name>News TV India</display-name></channel><channel id="3369"><display-name>TV13 Gujarati</display-name></channel><channel id="3370"><display-name>Gospel TV</display-name></channel><channel id="3371"><display-name>Ashwaveega News 24x7</display-name></channel><channel id="3378"><display-name>G18 News</display-name></channel><channel id="3379"><display-name>Headlines Kolkata</display-name></channel><channel id="3380"><display-name>Pradesh24 Gujarati</display-name></channel><channel id="3381"><display-name>Brio TV</display-name></channel><channel id="3382"><display-name>EPIC TV</display-name></channel><channel id="3383"><display-name>Epic Bharat</display-name></channel><channel id="3384"><display-name>EPIC Bhojpuri</display-name></channel><channel id="3385"><display-name>Gubbare</display-name></channel><channel id="3386"><display-name>P18 News </display-name></channel><channel id="3389"><display-name>INWILD</display-name></channel><channel id="3392"><display-name>INTRAVEL</display-name></channel><channel id="3393"><display-name>NTC TV</display-name></channel><channel id="3394"><display-name>Suriya TV</display-name></channel><channel id="3395"><display-name>Aaryaa TV</display-name></channel><channel id="3396"><display-name>Ultimate TV</display-name></channel><channel id="3401"><display-name>Swastik Stories</display-name></channel><channel id="3402"><display-name>DocuBay</display-name></channel><channel id="3405"><display-name>BHP News Gujarati</display-name></channel><channel id="3406"><display-name>Metro TV</display-name></channel><channel id="3409"><display-name>Roja TV</display-name></channel><channel id="3417"><display-name>Roja Movies</display-name></channel><channel id="3425"><display-name>Discovery Malayalam</display-name></channel><channel id="3427"><display-name>Sansad TV 1 HD</display-name></channel><channel id="3428"><display-name>Discovery HD Bengali</display-name></channel><channel id="3429"><display-name>Discovery Kannada</display-name></channel><channel id="3430"><display-name>Discovery Tamil</display-name></channel><channel id="3431"><display-name>Discovery HD Malayalam</display-name></channel><channel id="3432"><display-name>Discovery HD Kannada</display-name></channel><channel id="3433"><display-name>Discovery Kids Kannada</display-name></channel><channel id="3434"><display-name>Investigation Discovery HD Hindi</display-name></channel><channel id="3435"><display-name>Investigation Discovery HD English</display-name></channel><channel id="3436"><display-name>Cartoon Network HD+ Hindi</display-name></channel><channel id="3438"><display-name>Nation News</display-name></channel><channel id="3439"><display-name>Akhon kolkata</display-name></channel><channel id="3440"><display-name>TOI Global</display-name></channel><channel id="3443"><display-name>Raatdin Tripura</display-name></channel><channel id="3444"><display-name>Discovery HD Hindi</display-name></channel><channel id="3445"><display-name>Discovery HD Tamil</display-name></channel><channel id="3446"><display-name>Discovery HD Telugu</display-name></channel><channel id="3447"><display-name>Discovery Kids Telugu</display-name></channel><channel id="3448"><display-name>Discovery Kids Malayalam</display-name></channel><channel id="3450"><display-name>Animal Planet Tamil</display-name></channel><channel id="3451"><display-name>Animal Planet HD Hindi</display-name></channel><channel id="3452"><display-name>Investigation Discovery English</display-name></channel><channel id="3453"><display-name>Discovery Science Hindi</display-name></channel><channel id="3454"><display-name>Cartoon Network Marathi</display-name></channel><channel id="3455"><display-name>Cartoon Network HD+ Kannada</display-name></channel><channel id="3456"><display-name>Cartoon Network HD+ Malayalam</display-name></channel><channel id="3457"><display-name>Cartoon Network HD+ Marathi</display-name></channel><channel id="3458"><display-name>TLC HD Hindi</display-name></channel><channel id="3459"><display-name>Swastik TV</display-name></channel><channel id="3460"><display-name>G94 News</display-name></channel><channel id="3461"><display-name>Karnataka News Beat</display-name></channel><channel id="3462"><display-name>Nation Update</display-name></channel><channel id="3463"><display-name>Times of Maharashtra</display-name></channel><channel id="3464"><display-name>Guarantee News</display-name></channel><channel id="3467"><display-name>Green Gold TV</display-name></channel><channel id="3469"><display-name>NSC9 News</display-name></channel><channel id="3470"><display-name>GTC Punjabi</display-name></channel><channel id="3471"><display-name>Punjabi Shorts</display-name></channel><channel id="3478"><display-name>Stingray Classic Rock</display-name></channel><channel id="3479"><display-name>Stingray Greatest Hits</display-name></channel><channel id="3481"><display-name>Stingray Cozy Cafe</display-name></channel><channel id="3483"><display-name>Amar Ujala</display-name></channel><channel id="3484"><display-name>The Hind24 News</display-name></channel><channel id="3485"><display-name>National Today 24x7</display-name></channel><channel id="3486"><display-name>MP Today</display-name></channel><channel id="3490"><display-name>GTC News</display-name></channel><channel id="3492"><display-name>AlrightTV</display-name></channel><channel id="3493"><display-name>Shree Sanatan TV</display-name></channel><channel id="3497"><display-name>Village TV</display-name></channel><channel id="3498"><display-name>India Ahead</display-name></channel><channel id="3499"><display-name>World Chess</display-name></channel><channel id="3502"><display-name>Kadak</display-name></channel><channel id="3503"><display-name>Manas Bhakti</display-name></channel><channel id="3504"><display-name>R Maxx Kannada</display-name></channel><channel id="3505"><display-name>The Voice TV</display-name></channel><channel id="3508"><display-name>Valam TV Dayro</display-name></channel><channel id="3518"><display-name>Cine Jomjomat</display-name></channel><channel id="3519"><display-name>Shree Salangpur Dham</display-name></channel><channel id="3524"><display-name>Journy</display-name></channel><channel id="3526"><display-name>Rashtriya Pahal</display-name></channel><channel id="3529"><display-name>4 SiDES TV</display-name></channel><channel id="3530"><display-name>UIPM Pentathlon World Cup</display-name></channel></tv>